django_elephant-1.0.0.dist-info/DESCRIPTION.rst
django_elephant-1.0.0.dist-info/METADATA
django_elephant-1.0.0.dist-info/RECORD
django_elephant-1.0.0.dist-info/WHEEL
django_elephant-1.0.0.dist-info/metadata.json
django_elephant-1.0.0.dist-info/top_level.txt
elephant/__init__.py
elephant/exceptions.py
elephant/keys.py
