Metadata-Version: 2.0
Name: django-elephant
Version: 1.0.0
Summary: A simple cache for Django functions and methods
Home-page: https://github.com/jairhenrique/django-elephant
Author: Jair Henrique
Author-email: jair.henrique@gmail.com
License: MIT
Keywords: django cache
Platform: UNKNOWN
Classifier: Framework :: Django
Classifier: Intended Audience :: Developers
Classifier: License :: OSI Approved :: MIT License
Classifier: Operating System :: OS Independent
Classifier: Programming Language :: Python :: 2
Classifier: Programming Language :: Python :: 3
Requires-Dist: Django (>=1.4)
